{
  "experiment_name": "KBest_Advanced_Stats_RGB_Mini_Sunset_k20",
  "area_name": "sunset",
  "dataset_type": "mini",
  "feature_method": "advanced_stats",
  "k_features": 20,
  "dataset_info": {
    "data_directory": "/home/brusc/Projects/random_forest/dataset_rgb_salt_and_pepper_25/mini",
    "area_name": "sunset",
    "total_images": 15,
    "classes": {
      "garden": 5,
      "low_veg": 5,
      "trees": 5
    },
    "image_shape": [
      3,
      128,
      128
    ],
    "total_features_available": 54,
    "feature_method": "advanced_stats",
    "dataset_type": "rgb_mini",
    "k_features": 20
  },
  "feature_selection": {
    "method": "SelectKBest_k20",
    "num_features": 20,
    "selected_features": [
      "R_std",
      "R_var",
      "R_range",
      "R_mad",
      "R_grad_mean",
      "G_std",
      "G_var",
      "G_mad",
      "G_grad_mean",
      "B_mean",
      "B_std",
      "B_var",
      "B_skew",
      "B_kurt",
      "B_cv",
      "B_p50",
      "B_p75",
      "B_iqr",
      "B_mad",
      "B_grad_mean"
    ],
    "feature_scores": [
      0.6660067710067714,
      0.6660067710067714,
      0.32674270174270204,
      0.6863242313242321,
      0.36973452473452517,
      0.4831760831760834,
      0.4698427498427502,
      0.41682447182447246,
      0.37859455359455363,
      0.49478502978503003,
      0.33393846893846946,
      0.35393846893846925,
      0.4562448662448666,
      0.5145781995782,
      0.4712665112665113,
      0.4621707921707925,
      0.43857290857290887,
      0.48968401968402,
      0.3147898397898401,
      0.34298849298849277
    ]
  },
  "performance": {
    "mean_accuracy": 0.7999999999999999,
    "std_accuracy": 0.16329931618554522,
    "cv_scores": [
      0.6666666666666666,
      0.6666666666666666,
      1.0,
      0.6666666666666666,
      1.0
    ],
    "n_estimators": 5
  },
  "timestamp": "2025-07-16T18:05:55.961391"
}