{
  "experiment_name": "KBest_Advanced_Stats_RGB_Mini_Sunset_k5",
  "area_name": "sunset",
  "dataset_type": "mini",
  "feature_method": "advanced_stats",
  "k_features": 5,
  "dataset_info": {
    "data_directory": "/home/brusc/Projects/random_forest/dataset_rgb_uniform_40/mini",
    "area_name": "sunset",
    "total_images": 15,
    "classes": {
      "garden": 5,
      "low_veg": 5,
      "trees": 5
    },
    "image_shape": [
      3,
      128,
      128
    ],
    "total_features_available": 54,
    "feature_method": "advanced_stats",
    "dataset_type": "rgb_mini",
    "k_features": 5
  },
  "feature_selection": {
    "method": "SelectKBest_k5",
    "num_features": 5,
    "selected_features": [
      "R_std",
      "R_var",
      "R_grad_mean",
      "G_iqr",
      "G_grad_mean"
    ],
    "feature_scores": [
      0.8087051837051842,
      0.7753718503718507,
      0.9098162948162953,
      0.9698162948162949,
      1.006482961482962
    ]
  },
  "performance": {
    "mean_accuracy": 0.8666666666666666,
    "std_accuracy": 0.16329931618554522,
    "cv_scores": [
      1.0,
      0.6666666666666666,
      0.6666666666666666,
      1.0,
      1.0
    ],
    "n_estimators": 5
  },
  "timestamp": "2025-07-17T11:23:09.967882"
}