{
  "experiment_name": "hybrid_popolar_k2_WithModel",
  "config": {
    "dataset_path": "/home/brusc/Projects/random_forest/datasets/dataset_rgb_speckle_55/small",
    "area_name": "popolar",
    "feature_method": "hybrid",
    "k_features": 2,
    "output_dir": "/home/brusc/Projects/random_forest/experiments_organized/speckle_output/dataset_rgb_speckle_55/popolar/small/k2/hybrid",
    "n_estimators": 10,
    "test_size": 0.2,
    "random_state": 42,
    "cv_folds": 5
  },
  "dataset_info": {
    "data_directory": "/home/brusc/Projects/random_forest/datasets/dataset_rgb_speckle_55/small",
    "area_name": "popolar",
    "total_images": 45,
    "classes": {
      "low_veg": 15,
      "trees": 15,
      "water": 15
    },
    "image_shape": [
      3,
      128,
      128
    ],
    "total_features_available": 540,
    "feature_method": "hybrid",
    "dataset_type": "small",
    "k_features": 2
  },
  "feature_selection": {
    "method": "SelectKBest_k2",
    "num_features": 2,
    "selected_features": [
      "R_wst_std_0",
      "G_wst_std_0"
    ],
    "feature_scores": [
      1.0522217678249741,
      0.9736236375601772
    ]
  },
  "performance": {
    "test_accuracy": 1.0,
    "cv_mean_accuracy": 0.9777777777777779,
    "cv_std_accuracy": 0.04444444444444447,
    "cv_scores": [
      1.0,
      1.0,
      1.0,
      1.0,
      0.8888888888888888
    ],
    "classification_report": {
      "low_veg": {
        "precision": 1.0,
        "recall": 1.0,
        "f1-score": 1.0,
        "support": 3.0
      },
      "trees": {
        "precision": 1.0,
        "recall": 1.0,
        "f1-score": 1.0,
        "support": 3.0
      },
      "water": {
        "precision": 1.0,
        "recall": 1.0,
        "f1-score": 1.0,
        "support": 3.0
      },
      "accuracy": 1.0,
      "macro avg": {
        "precision": 1.0,
        "recall": 1.0,
        "f1-score": 1.0,
        "support": 9.0
      },
      "weighted avg": {
        "precision": 1.0,
        "recall": 1.0,
        "f1-score": 1.0,
        "support": 9.0
      }
    },
    "confusion_matrix": [
      [
        3,
        0,
        0
      ],
      [
        0,
        3,
        0
      ],
      [
        0,
        0,
        3
      ]
    ]
  },
  "model_files": {
    "trained_model": "trained_model.joblib",
    "scaler": "scaler.joblib",
    "feature_selector": "feature_selector.joblib",
    "feature_names": "feature_names.json"
  },
  "timestamp": "2025-07-22T03:04:32.394120"
}